t3api_utils/__init__.py
t3api_utils/exceptions.py
t3api_utils/interfaces.py
t3api_utils/logging.py
t3api_utils/api/__init__.py
t3api_utils/api/client.py
t3api_utils/api/interfaces.py
t3api_utils/api/operations.py
t3api_utils/api/parallel.py
t3api_utils/auth/__init__.py
t3api_utils/auth/interfaces.py
t3api_utils/auth/utils.py
t3api_utils/cli/__init__.py
t3api_utils/cli/consts.py
t3api_utils/cli/utils.py
t3api_utils/collection/__init__.py
t3api_utils/collection/utils.py
t3api_utils/db/__init__.py
t3api_utils/db/consts.py
t3api_utils/db/utils.py
t3api_utils/file/__init__.py
t3api_utils/file/consts.py
t3api_utils/file/utils.py
t3api_utils/http/__init__.py
t3api_utils/http/utils.py
t3api_utils/inspector/__init__.py
t3api_utils/inspector/app.py
t3api_utils/main/__init__.py
t3api_utils/main/handlers.py
t3api_utils/main/utils.py
t3api_utils/openapi/__init__.py
t3api_utils/openapi/collection_picker.py
t3api_utils/openapi/spec_fetcher.py
t3api_utils/style/__init__.py
t3api_utils/style/console.py
t3api_utils/style/messages.py
t3api_utils/style/styles.py
t3api_utils-1.0.0.dist-info/licenses/LICENSE
t3api_utils-1.0.0.dist-info/METADATA
t3api_utils-1.0.0.dist-info/WHEEL
t3api_utils-1.0.0.dist-info/top_level.txt
t3api_utils-1.0.0.dist-info/RECORD
