Metadata-Version: 2.4
Name: t3api-utils
Version: 1.0.0
Summary: Utility functions and helpers for the T3 API ecosystem
Author-email: Matt Frisbie <matt@classvsoftware.com>
License-Expression: GPL-3.0-only
Project-URL: Homepage, https://github.com/classvsoftware/t3api-python-utils
Keywords: t3,metrc,utils,helpers,track and trace
Classifier: Development Status :: 5 - Production/Stable
Classifier: Programming Language :: Python :: 3
Classifier: Programming Language :: Python :: 3.12
Classifier: Operating System :: OS Independent
Requires-Python: >=3.12
License-File: LICENSE
Requires-Dist: certifi>=2023.7.22
Requires-Dist: python-dotenv>=1.0.0
Requires-Dist: rich>=13.0.0
Requires-Dist: questionary>=2.0.0
Requires-Dist: typer>=0.16.0
Requires-Dist: duckdb>=1.3.0
Requires-Dist: pyarrow>=17.0.0
Requires-Dist: httpx>=0.25.0
Requires-Dist: textual>=6.0.0
Requires-Dist: pyotp>=2.8.0
Provides-Extra: dev
Requires-Dist: mypy>=1.14.1; extra == "dev"
Requires-Dist: pytest>=8.3.5; extra == "dev"
Requires-Dist: pytest-asyncio>=1.2.0; extra == "dev"
Dynamic: license-file
